setup.py
ChromeDecrypt/__init__.py
ChromeDecrypt/decryptor.py
ChromeDecrypt/reader.py
ChromeDecrypt/sqlite.py
ChromeDecrypt.egg-info/PKG-INFO
ChromeDecrypt.egg-info/SOURCES.txt
ChromeDecrypt.egg-info/dependency_links.txt
ChromeDecrypt.egg-info/requires.txt
ChromeDecrypt.egg-info/top_level.txt